enpix/__init__.py
enpix/random_set.py
enpix-1.0.4.dist-info/LICENSE
enpix-1.0.4.dist-info/METADATA
enpix-1.0.4.dist-info/WHEEL
enpix-1.0.4.dist-info/top_level.txt
enpix-1.0.4.dist-info/RECORD
