Metadata-Version: 2.1
Name: enpix
Version: 1.0.4
Summary: Strongest Image Encryption
Home-page: https://github.com/ThisIsNSH/Enpix/Python
Author: Nishant Hada
Author-email: hadanis.singh@gmail.com
License: UNKNOWN
Platform: UNKNOWN
Classifier: Programming Language :: Python :: 3
Classifier: License :: OSI Approved :: MIT License
Classifier: Operating System :: OS Independent
Requires-Python: >=3.6
